<?xml version="1.0" encoding="utf-8"?>
<!DOCTYPE hibernate-mapping PUBLIC "-//Hibernate/Hibernate Mapping DTD 3.0//EN"
"http://hibernate.sourceforge.net/hibernate-mapping-3.0.dtd">
<!-- 
    Mapping file autogenerated by MyEclipse Persistence Tools
-->
<hibernate-mapping>
    <class name="com.business.v2.question.TbQuestionListeningQuestionOption" table="tb_question_listening_question_option" catalog="jn_spark_online">
        <id name="id" type="java.lang.String">
            <column name="id" length="32" />
            <generator class="assigned" />
        </id>
        <property name="questionId" type="java.lang.String">
            <column name="question_id" length="32">
                <comment>听力题目</comment>
            </column>
        </property>
        <property name="prefix" type="java.lang.String">
            <column name="prefix" length="8">
                <comment>选项：如ABCD</comment>
            </column>
        </property>
        <property name="content" type="java.lang.String">
            <column name="content" length="65535">
                <comment>选项内容</comment>
            </column>
        </property>
        <property name="isAnswer" type="java.lang.String">
            <column name="is_answer" length="1">
                <comment>是否答案：0否，1是</comment>
            </column>
        </property>
    </class>
</hibernate-mapping>
